Metadata-Version: 2.1
Name: ungleich-cli
Version: 1.0.0
Summary: A Python package for ungleich dns administration.
Home-page: UNKNOWN
Author: William Colmenares
Author-email: colmenares.william@gmail.com
License: MIT
Platform: UNKNOWN
Classifier: License :: OSI Approved :: MIT License
Classifier: Programming Language :: Python :: 3
Classifier: Programming Language :: Python :: 3.6
